pythonpine/__init__.py
pythonpine/benchmark.py
pythonpine/cycles.py
pythonpine/experimental.py
pythonpine/meta.py
pythonpine/momentum.py
pythonpine/momentum_v2.py
pythonpine/normalize.py
pythonpine/price_action.py
pythonpine/price_action_v2.py
pythonpine/price_fetcher.py
pythonpine/setup.py
pythonpine/statistical.py
pythonpine/time_session.py
pythonpine/trend.py
pythonpine/trend_v2.py
pythonpine/utils.py
pythonpine/volatility.py
pythonpine/volatility_v2.py
pythonpine/volume.py
pythonpine-2.0.1.dist-info/licenses/LICENSE
pythonpine-2.0.1.dist-info/METADATA
pythonpine-2.0.1.dist-info/WHEEL
pythonpine-2.0.1.dist-info/top_level.txt
pythonpine-2.0.1.dist-info/RECORD
