Metadata-Version: 2.4
Name: pythonpine
Version: 2.0.1
Summary: High-performance vectorized Pine Script indicators for ML and backtesting
Author: Kushal Garg
License: MIT
Project-URL: Homepage, https://github.com/kshlgrg/pythonpine
Project-URL: Repository, https://github.com/kshlgrg/pythonpine
Keywords: technical-analysis,trading,indicators,pine-script,machine-learning,quantitative-finance,RSI,MACD,ATR
Classifier: Development Status :: 4 - Beta
Classifier: Intended Audience :: Financial and Insurance Industry
Classifier: License :: OSI Approved :: MIT License
Classifier: Operating System :: OS Independent
Classifier: Programming Language :: Python :: 3
Classifier: Programming Language :: Python :: 3.8
Classifier: Programming Language :: Python :: 3.9
Classifier: Programming Language :: Python :: 3.10
Classifier: Programming Language :: Python :: 3.11
Classifier: Programming Language :: Python :: 3.12
Classifier: Topic :: Office/Business :: Financial :: Investment
Requires-Python: >=3.8
License-File: LICENSE
Requires-Dist: numpy>=1.20.0
Requires-Dist: pandas>=1.3.0
Provides-Extra: ml
Requires-Dist: scikit-learn>=1.0.0; extra == "ml"
Provides-Extra: all
Requires-Dist: scikit-learn>=1.0.0; extra == "all"
Dynamic: license-file
